{
    "key": "group_625de2e2aaa29",
    "title": "Sitewide Data",
    "fields": [
        {
            "key": "field_66a3e04bba63b",
            "label": "Hours",
            "name": "",
            "aria-label": "",
            "type": "tab",
            "instructions": "",
            "required": 0,
            "conditional_logic": 0,
            "wrapper": {
                "width": "",
                "class": "",
                "id": ""
            },
            "placement": "top",
            "endpoint": 0,
            "selected": 0
        },
        {
            "key": "field_625de2f40c412",
            "label": "Hours",
            "name": "hours",
            "aria-label": "",
            "type": "group",
            "instructions": "",
            "required": 0,
            "conditional_logic": 0,
            "wrapper": {
                "width": "",
                "class": "",
                "id": ""
            },
            "layout": "block",
            "sub_fields": [
                {
                    "key": "field_62744c88de3f9",
                    "label": "Monday Hours",
                    "name": "monday_hours",
                    "aria-label": "",
                    "type": "group",
                    "instructions": "",
                    "required": 0,
                    "conditional_logic": 0,
                    "wrapper": {
                        "width": "",
                        "class": "",
                        "id": ""
                    },
                    "layout": "table",
                    "sub_fields": [
                        {
                            "key": "field_62744c96de3fa",
                            "label": "Open",
                            "name": "open",
                            "aria-label": "",
                            "type": "time_picker",
                            "instructions": "",
                            "required": 0,
                            "conditional_logic": 0,
                            "wrapper": {
                                "width": "",
                                "class": "",
                                "id": ""
                            },
                            "display_format": "g:i a",
                            "return_format": "g:i a"
                        },
                        {
                            "key": "field_62744c9dde3fb",
                            "label": "Close",
                            "name": "close",
                            "aria-label": "",
                            "type": "time_picker",
                            "instructions": "",
                            "required": 0,
                            "conditional_logic": 0,
                            "wrapper": {
                                "width": "",
                                "class": "",
                                "id": ""
                            },
                            "display_format": "g:i a",
                            "return_format": "g:i a"
                        }
                    ]
                },
                {
                    "key": "field_62744cacde3fc",
                    "label": "Tuesday Hours",
                    "name": "tuesday_hours",
                    "aria-label": "",
                    "type": "group",
                    "instructions": "",
                    "required": 0,
                    "conditional_logic": 0,
                    "wrapper": {
                        "width": "",
                        "class": "",
                        "id": ""
                    },
                    "layout": "table",
                    "sub_fields": [
                        {
                            "key": "field_62744cacde3fd",
                            "label": "Open",
                            "name": "open",
                            "aria-label": "",
                            "type": "time_picker",
                            "instructions": "",
                            "required": 0,
                            "conditional_logic": 0,
                            "wrapper": {
                                "width": "",
                                "class": "",
                                "id": ""
                            },
                            "display_format": "g:i a",
                            "return_format": "g:i a"
                        },
                        {
                            "key": "field_62744cacde3fe",
                            "label": "Close",
                            "name": "close",
                            "aria-label": "",
                            "type": "time_picker",
                            "instructions": "",
                            "required": 0,
                            "conditional_logic": 0,
                            "wrapper": {
                                "width": "",
                                "class": "",
                                "id": ""
                            },
                            "display_format": "g:i a",
                            "return_format": "g:i a"
                        }
                    ]
                },
                {
                    "key": "field_62744cb9de3ff",
                    "label": "Wednesday Hours",
                    "name": "wednesday_hours",
                    "aria-label": "",
                    "type": "group",
                    "instructions": "",
                    "required": 0,
                    "conditional_logic": 0,
                    "wrapper": {
                        "width": "",
                        "class": "",
                        "id": ""
                    },
                    "layout": "table",
                    "sub_fields": [
                        {
                            "key": "field_62744cb9de400",
                            "label": "Open",
                            "name": "open",
                            "aria-label": "",
                            "type": "time_picker",
                            "instructions": "",
                            "required": 0,
                            "conditional_logic": 0,
                            "wrapper": {
                                "width": "",
                                "class": "",
                                "id": ""
                            },
                            "display_format": "g:i a",
                            "return_format": "g:i a"
                        },
                        {
                            "key": "field_62744cb9de401",
                            "label": "Close",
                            "name": "close",
                            "aria-label": "",
                            "type": "time_picker",
                            "instructions": "",
                            "required": 0,
                            "conditional_logic": 0,
                            "wrapper": {
                                "width": "",
                                "class": "",
                                "id": ""
                            },
                            "display_format": "g:i a",
                            "return_format": "g:i a"
                        }
                    ]
                },
                {
                    "key": "field_62744cc7de402",
                    "label": "Thursday Hours",
                    "name": "thursday_hours",
                    "aria-label": "",
                    "type": "group",
                    "instructions": "",
                    "required": 0,
                    "conditional_logic": 0,
                    "wrapper": {
                        "width": "",
                        "class": "",
                        "id": ""
                    },
                    "layout": "table",
                    "sub_fields": [
                        {
                            "key": "field_62744cc7de403",
                            "label": "Open",
                            "name": "open",
                            "aria-label": "",
                            "type": "time_picker",
                            "instructions": "",
                            "required": 0,
                            "conditional_logic": 0,
                            "wrapper": {
                                "width": "",
                                "class": "",
                                "id": ""
                            },
                            "display_format": "g:i a",
                            "return_format": "g:i a"
                        },
                        {
                            "key": "field_62744cc7de404",
                            "label": "Close",
                            "name": "close",
                            "aria-label": "",
                            "type": "time_picker",
                            "instructions": "",
                            "required": 0,
                            "conditional_logic": 0,
                            "wrapper": {
                                "width": "",
                                "class": "",
                                "id": ""
                            },
                            "display_format": "g:i a",
                            "return_format": "g:i a"
                        }
                    ]
                },
                {
                    "key": "field_62744cd7de405",
                    "label": "Friday Hours",
                    "name": "friday_hours",
                    "aria-label": "",
                    "type": "group",
                    "instructions": "",
                    "required": 0,
                    "conditional_logic": 0,
                    "wrapper": {
                        "width": "",
                        "class": "",
                        "id": ""
                    },
                    "layout": "table",
                    "sub_fields": [
                        {
                            "key": "field_62744cd7de406",
                            "label": "Open",
                            "name": "open",
                            "aria-label": "",
                            "type": "time_picker",
                            "instructions": "",
                            "required": 0,
                            "conditional_logic": 0,
                            "wrapper": {
                                "width": "",
                                "class": "",
                                "id": ""
                            },
                            "display_format": "g:i a",
                            "return_format": "g:i a"
                        },
                        {
                            "key": "field_62744cd7de407",
                            "label": "Close",
                            "name": "close",
                            "aria-label": "",
                            "type": "time_picker",
                            "instructions": "",
                            "required": 0,
                            "conditional_logic": 0,
                            "wrapper": {
                                "width": "",
                                "class": "",
                                "id": ""
                            },
                            "display_format": "g:i a",
                            "return_format": "g:i a"
                        }
                    ]
                },
                {
                    "key": "field_62744ce8de408",
                    "label": "Saturday Hours",
                    "name": "saturday_hours",
                    "aria-label": "",
                    "type": "group",
                    "instructions": "",
                    "required": 0,
                    "conditional_logic": 0,
                    "wrapper": {
                        "width": "",
                        "class": "",
                        "id": ""
                    },
                    "layout": "table",
                    "sub_fields": [
                        {
                            "key": "field_62744ce8de409",
                            "label": "Open",
                            "name": "open",
                            "aria-label": "",
                            "type": "time_picker",
                            "instructions": "",
                            "required": 0,
                            "conditional_logic": 0,
                            "wrapper": {
                                "width": "",
                                "class": "",
                                "id": ""
                            },
                            "display_format": "g:i a",
                            "return_format": "g:i a"
                        },
                        {
                            "key": "field_62744ce8de40a",
                            "label": "Close",
                            "name": "close",
                            "aria-label": "",
                            "type": "time_picker",
                            "instructions": "",
                            "required": 0,
                            "conditional_logic": 0,
                            "wrapper": {
                                "width": "",
                                "class": "",
                                "id": ""
                            },
                            "display_format": "g:i a",
                            "return_format": "g:i a"
                        }
                    ]
                },
                {
                    "key": "field_62744cf5de40b",
                    "label": "Sunday Hours",
                    "name": "sunday_hours",
                    "aria-label": "",
                    "type": "group",
                    "instructions": "",
                    "required": 0,
                    "conditional_logic": 0,
                    "wrapper": {
                        "width": "",
                        "class": "",
                        "id": ""
                    },
                    "layout": "table",
                    "sub_fields": [
                        {
                            "key": "field_62744cf5de40c",
                            "label": "Open",
                            "name": "open",
                            "aria-label": "",
                            "type": "time_picker",
                            "instructions": "",
                            "required": 0,
                            "conditional_logic": 0,
                            "wrapper": {
                                "width": "",
                                "class": "",
                                "id": ""
                            },
                            "display_format": "g:i a",
                            "return_format": "g:i a"
                        },
                        {
                            "key": "field_62744cf5de40d",
                            "label": "Close",
                            "name": "close",
                            "aria-label": "",
                            "type": "time_picker",
                            "instructions": "",
                            "required": 0,
                            "conditional_logic": 0,
                            "wrapper": {
                                "width": "",
                                "class": "",
                                "id": ""
                            },
                            "display_format": "g:i a",
                            "return_format": "g:i a"
                        }
                    ]
                },
                {
                    "key": "field_625de40a0c422",
                    "label": "Holidays",
                    "name": "holidays",
                    "aria-label": "",
                    "type": "repeater",
                    "instructions": "",
                    "required": 0,
                    "conditional_logic": 0,
                    "wrapper": {
                        "width": "",
                        "class": "",
                        "id": ""
                    },
                    "collapsed": "",
                    "min": 0,
                    "max": 0,
                    "layout": "table",
                    "button_label": "Add Row",
                    "sub_fields": [
                        {
                            "key": "field_625de4170c423",
                            "label": "Start Date",
                            "name": "start_date",
                            "aria-label": "",
                            "type": "date_picker",
                            "instructions": "",
                            "required": 0,
                            "conditional_logic": 0,
                            "wrapper": {
                                "width": "",
                                "class": "",
                                "id": ""
                            },
                            "display_format": "m\/d\/Y",
                            "return_format": "m\/d\/Y",
                            "first_day": 1,
                            "parent_repeater": "field_625de40a0c422"
                        },
                        {
                            "key": "field_625de4230c424",
                            "label": "End Date",
                            "name": "end_date",
                            "aria-label": "",
                            "type": "date_picker",
                            "instructions": "",
                            "required": 0,
                            "conditional_logic": 0,
                            "wrapper": {
                                "width": "",
                                "class": "",
                                "id": ""
                            },
                            "display_format": "m\/d\/Y",
                            "return_format": "m\/d\/Y",
                            "first_day": 1,
                            "parent_repeater": "field_625de40a0c422"
                        },
                        {
                            "key": "field_625de503b2789",
                            "label": "Closed?",
                            "name": "closed",
                            "aria-label": "",
                            "type": "true_false",
                            "instructions": "",
                            "required": 0,
                            "conditional_logic": 0,
                            "wrapper": {
                                "width": "",
                                "class": "",
                                "id": ""
                            },
                            "message": "",
                            "default_value": 1,
                            "ui": 0,
                            "ui_on_text": "",
                            "ui_off_text": "",
                            "parent_repeater": "field_625de40a0c422"
                        },
                        {
                            "key": "field_625de4320c425",
                            "label": "Opening Hours",
                            "name": "opening_hours",
                            "aria-label": "",
                            "type": "time_picker",
                            "instructions": "",
                            "required": 0,
                            "conditional_logic": [
                                [
                                    {
                                        "field": "field_625de503b2789",
                                        "operator": "!=",
                                        "value": "1"
                                    }
                                ]
                            ],
                            "wrapper": {
                                "width": "",
                                "class": "",
                                "id": ""
                            },
                            "display_format": "g:i a",
                            "return_format": "g:i a",
                            "parent_repeater": "field_625de40a0c422"
                        },
                        {
                            "key": "field_625de43d0c426",
                            "label": "Closing Hours",
                            "name": "closing_hours",
                            "aria-label": "",
                            "type": "time_picker",
                            "instructions": "",
                            "required": 0,
                            "conditional_logic": [
                                [
                                    {
                                        "field": "field_625de503b2789",
                                        "operator": "!=",
                                        "value": "1"
                                    }
                                ]
                            ],
                            "wrapper": {
                                "width": "",
                                "class": "",
                                "id": ""
                            },
                            "display_format": "g:i a",
                            "return_format": "g:i a",
                            "parent_repeater": "field_625de40a0c422"
                        }
                    ],
                    "rows_per_page": 20
                }
            ]
        },
        {
            "key": "field_66a3e058ba63c",
            "label": "Contact Info",
            "name": "",
            "aria-label": "",
            "type": "tab",
            "instructions": "",
            "required": 0,
            "conditional_logic": 0,
            "wrapper": {
                "width": "",
                "class": "",
                "id": ""
            },
            "placement": "top",
            "endpoint": 0,
            "selected": 0
        },
        {
            "key": "field_625de75f6bb71",
            "label": "Address",
            "name": "address",
            "aria-label": "",
            "type": "group",
            "instructions": "",
            "required": 0,
            "conditional_logic": 0,
            "wrapper": {
                "width": "",
                "class": "",
                "id": ""
            },
            "layout": "block",
            "sub_fields": [
                {
                    "key": "field_625de7686bb72",
                    "label": "Address Text",
                    "name": "address_text",
                    "aria-label": "",
                    "type": "textarea",
                    "instructions": "",
                    "required": 0,
                    "conditional_logic": 0,
                    "wrapper": {
                        "width": "",
                        "class": "",
                        "id": ""
                    },
                    "default_value": "",
                    "placeholder": "",
                    "maxlength": "",
                    "rows": "",
                    "new_lines": ""
                },
                {
                    "key": "field_625de76f6bb73",
                    "label": "Address Link",
                    "name": "address_link",
                    "aria-label": "",
                    "type": "link",
                    "instructions": "",
                    "required": 0,
                    "conditional_logic": 0,
                    "wrapper": {
                        "width": "",
                        "class": "",
                        "id": ""
                    },
                    "return_format": "array"
                }
            ]
        },
        {
            "key": "field_625de77b6bb74",
            "label": "Phone Number",
            "name": "phone_number",
            "aria-label": "",
            "type": "text",
            "instructions": "",
            "required": 0,
            "conditional_logic": 0,
            "wrapper": {
                "width": "",
                "class": "",
                "id": ""
            },
            "default_value": "",
            "placeholder": "",
            "prepend": "",
            "append": "",
            "maxlength": ""
        },
        {
            "key": "field_625de7906bb75",
            "label": "Contact Email",
            "name": "contact_email",
            "aria-label": "",
            "type": "email",
            "instructions": "",
            "required": 0,
            "conditional_logic": 0,
            "wrapper": {
                "width": "",
                "class": "",
                "id": ""
            },
            "default_value": "",
            "placeholder": "",
            "prepend": "",
            "append": ""
        },
        {
            "key": "field_66a3e08cba63f",
            "label": "Artist Interventions",
            "name": "",
            "aria-label": "",
            "type": "tab",
            "instructions": "",
            "required": 0,
            "conditional_logic": 0,
            "wrapper": {
                "width": "",
                "class": "",
                "id": ""
            },
            "placement": "top",
            "endpoint": 0,
            "selected": 0
        },
        {
            "key": "field_62a11638f3015",
            "label": "Artist Intervention",
            "name": "artist_intervention",
            "aria-label": "",
            "type": "group",
            "instructions": "If a screensaver image\/video exists, or a flyout image\/video exists then they will show up on the site. If they dont exist, then they wont show up.",
            "required": 0,
            "conditional_logic": 0,
            "wrapper": {
                "width": "",
                "class": "",
                "id": ""
            },
            "layout": "block",
            "sub_fields": [
                {
                    "key": "field_62a1164bf3016",
                    "label": "Screensaver",
                    "name": "screensaver",
                    "aria-label": "",
                    "type": "group",
                    "instructions": "",
                    "required": 0,
                    "conditional_logic": 0,
                    "wrapper": {
                        "width": "",
                        "class": "",
                        "id": ""
                    },
                    "layout": "block",
                    "sub_fields": [
                        {
                            "key": "field_62ac9901afb8a",
                            "label": "Title",
                            "name": "title",
                            "aria-label": "",
                            "type": "text",
                            "instructions": "",
                            "required": 0,
                            "conditional_logic": 0,
                            "wrapper": {
                                "width": "",
                                "class": "",
                                "id": ""
                            },
                            "default_value": "",
                            "placeholder": "",
                            "prepend": "",
                            "append": "",
                            "maxlength": ""
                        },
                        {
                            "key": "field_62ac9907afb8b",
                            "label": "Year",
                            "name": "year",
                            "aria-label": "",
                            "type": "text",
                            "instructions": "",
                            "required": 0,
                            "conditional_logic": 0,
                            "wrapper": {
                                "width": "",
                                "class": "",
                                "id": ""
                            },
                            "default_value": "",
                            "placeholder": "",
                            "prepend": "",
                            "append": "",
                            "maxlength": ""
                        },
                        {
                            "key": "field_62ac990dafb8c",
                            "label": "Artist Name",
                            "name": "artist_name",
                            "aria-label": "",
                            "type": "text",
                            "instructions": "",
                            "required": 0,
                            "conditional_logic": 0,
                            "wrapper": {
                                "width": "",
                                "class": "",
                                "id": ""
                            },
                            "default_value": "",
                            "placeholder": "",
                            "prepend": "",
                            "append": "",
                            "maxlength": ""
                        },
                        {
                            "key": "field_62ac9912afb8d",
                            "label": "Exhibition Link",
                            "name": "exhibition_link",
                            "aria-label": "",
                            "type": "post_object",
                            "instructions": "",
                            "required": 0,
                            "conditional_logic": 0,
                            "wrapper": {
                                "width": "",
                                "class": "",
                                "id": ""
                            },
                            "post_type": [
                                "exhibition"
                            ],
                            "taxonomy": "",
                            "allow_null": 0,
                            "multiple": 0,
                            "return_format": "",
                            "ui": 1,
                            "bidirectional_target": []
                        },
                        {
                            "key": "field_62b541d355333",
                            "label": "PNG Stamps",
                            "name": "png_stamps",
                            "aria-label": "",
                            "type": "gallery",
                            "instructions": "If any image exists, the screensaver will be a small-ish png that is sequentially repeated in random spots on the page. Overrides image and video.",
                            "required": 0,
                            "conditional_logic": 0,
                            "wrapper": {
                                "width": "",
                                "class": "",
                                "id": ""
                            },
                            "return_format": "array",
                            "preview_size": "medium",
                            "insert": "append",
                            "library": "all",
                            "min": "",
                            "max": "",
                            "min_width": "",
                            "min_height": "",
                            "min_size": "",
                            "max_width": "",
                            "max_height": "",
                            "max_size": "",
                            "mime_types": ".jpg, .png, .svg"
                        },
                        {
                            "key": "field_62a1170e42155",
                            "label": "Video",
                            "name": "video",
                            "aria-label": "",
                            "type": "file",
                            "instructions": "If exists, screensaver will be a video. Is overridden by PNG stamp, but overrides image.",
                            "required": 0,
                            "conditional_logic": 0,
                            "wrapper": {
                                "width": "",
                                "class": "",
                                "id": ""
                            },
                            "return_format": "array",
                            "library": "all",
                            "min_size": "",
                            "max_size": "",
                            "mime_types": ".mp4"
                        },
                        {
                            "key": "field_62a1170942154",
                            "label": "Image",
                            "name": "image",
                            "aria-label": "",
                            "type": "image",
                            "instructions": "If exists, screensaver will be an image. Is overridden by PNG Stamp and video.",
                            "required": 0,
                            "conditional_logic": 0,
                            "wrapper": {
                                "width": "",
                                "class": "",
                                "id": ""
                            },
                            "return_format": "array",
                            "preview_size": "medium",
                            "library": "all",
                            "min_width": "",
                            "min_height": "",
                            "min_size": "",
                            "max_width": "",
                            "max_height": "",
                            "max_size": "",
                            "mime_types": ""
                        },
                        {
                            "key": "field_62a1171c42156",
                            "label": "Position",
                            "name": "position",
                            "aria-label": "",
                            "type": "select",
                            "instructions": "",
                            "required": 0,
                            "conditional_logic": 0,
                            "wrapper": {
                                "width": "",
                                "class": "",
                                "id": ""
                            },
                            "choices": {
                                "object-cover": "Cover",
                                "object-contain": "Contain"
                            },
                            "default_value": "object-cover",
                            "allow_null": 0,
                            "multiple": 0,
                            "ui": 0,
                            "return_format": "value",
                            "ajax": 0,
                            "placeholder": ""
                        }
                    ]
                },
                {
                    "key": "field_62ac9935afb8e",
                    "label": "Flyout",
                    "name": "flyout",
                    "aria-label": "",
                    "type": "group",
                    "instructions": "",
                    "required": 0,
                    "conditional_logic": 0,
                    "wrapper": {
                        "width": "",
                        "class": "",
                        "id": ""
                    },
                    "layout": "block",
                    "sub_fields": [
                        {
                            "key": "field_62ac9935afb8f",
                            "label": "Title",
                            "name": "title",
                            "aria-label": "",
                            "type": "text",
                            "instructions": "",
                            "required": 0,
                            "conditional_logic": 0,
                            "wrapper": {
                                "width": "",
                                "class": "",
                                "id": ""
                            },
                            "default_value": "",
                            "placeholder": "",
                            "prepend": "",
                            "append": "",
                            "maxlength": ""
                        },
                        {
                            "key": "field_62ac9935afb90",
                            "label": "Year",
                            "name": "year",
                            "aria-label": "",
                            "type": "text",
                            "instructions": "",
                            "required": 0,
                            "conditional_logic": 0,
                            "wrapper": {
                                "width": "",
                                "class": "",
                                "id": ""
                            },
                            "default_value": "",
                            "placeholder": "",
                            "prepend": "",
                            "append": "",
                            "maxlength": ""
                        },
                        {
                            "key": "field_62ac9935afb91",
                            "label": "Artist Name",
                            "name": "artist_name",
                            "aria-label": "",
                            "type": "text",
                            "instructions": "",
                            "required": 0,
                            "conditional_logic": 0,
                            "wrapper": {
                                "width": "",
                                "class": "",
                                "id": ""
                            },
                            "default_value": "",
                            "placeholder": "",
                            "prepend": "",
                            "append": "",
                            "maxlength": ""
                        },
                        {
                            "key": "field_62ac9935afb92",
                            "label": "Exhibition Link",
                            "name": "exhibition_link",
                            "aria-label": "",
                            "type": "post_object",
                            "instructions": "",
                            "required": 0,
                            "conditional_logic": 0,
                            "wrapper": {
                                "width": "",
                                "class": "",
                                "id": ""
                            },
                            "post_type": [
                                "exhibition"
                            ],
                            "taxonomy": "",
                            "allow_null": 0,
                            "multiple": 0,
                            "return_format": "object",
                            "ui": 1,
                            "bidirectional_target": []
                        },
                        {
                            "key": "field_62ac9935afb93",
                            "label": "Image",
                            "name": "image",
                            "aria-label": "",
                            "type": "image",
                            "instructions": "",
                            "required": 0,
                            "conditional_logic": 0,
                            "wrapper": {
                                "width": "",
                                "class": "",
                                "id": ""
                            },
                            "return_format": "array",
                            "preview_size": "medium",
                            "library": "all",
                            "min_width": "",
                            "min_height": "",
                            "min_size": "",
                            "max_width": "",
                            "max_height": "",
                            "max_size": "",
                            "mime_types": ""
                        },
                        {
                            "key": "field_62ac9935afb94",
                            "label": "Video",
                            "name": "video",
                            "aria-label": "",
                            "type": "file",
                            "instructions": "",
                            "required": 0,
                            "conditional_logic": 0,
                            "wrapper": {
                                "width": "",
                                "class": "",
                                "id": ""
                            },
                            "return_format": "array",
                            "library": "all",
                            "min_size": "",
                            "max_size": "",
                            "mime_types": ".mp4"
                        },
                        {
                            "key": "field_62ac9935afb95",
                            "label": "Position",
                            "name": "position",
                            "aria-label": "",
                            "type": "select",
                            "instructions": "",
                            "required": 0,
                            "conditional_logic": 0,
                            "wrapper": {
                                "width": "",
                                "class": "",
                                "id": ""
                            },
                            "choices": {
                                "object-cover": "Cover",
                                "object-contain": "Contain"
                            },
                            "default_value": "object-cover",
                            "allow_null": 0,
                            "multiple": 0,
                            "ui": 0,
                            "ajax": 0,
                            "return_format": "value",
                            "placeholder": ""
                        }
                    ]
                }
            ]
        },
        {
            "key": "field_66a3e079ba63e",
            "label": "Other",
            "name": "",
            "aria-label": "",
            "type": "tab",
            "instructions": "",
            "required": 0,
            "conditional_logic": 0,
            "wrapper": {
                "width": "",
                "class": "",
                "id": ""
            },
            "placement": "top",
            "endpoint": 0,
            "selected": 0
        },
        {
            "key": "field_62a10cb9d9d0a",
            "label": "Tickets Link",
            "name": "tickets_link",
            "aria-label": "",
            "type": "link",
            "instructions": "",
            "required": 0,
            "conditional_logic": 0,
            "wrapper": {
                "width": "",
                "class": "",
                "id": ""
            },
            "return_format": "array"
        },
        {
            "key": "field_6304eddc0427a",
            "label": "Related Items Text",
            "name": "related_items_text",
            "aria-label": "",
            "type": "text",
            "instructions": "",
            "required": 1,
            "conditional_logic": 0,
            "wrapper": {
                "width": "",
                "class": "",
                "id": ""
            },
            "default_value": "",
            "placeholder": "",
            "prepend": "",
            "append": "",
            "maxlength": ""
        },
        {
            "key": "field_630f84670c330",
            "label": "Ex Oficio Items",
            "name": "ex_oficio_items",
            "aria-label": "",
            "type": "repeater",
            "instructions": "These items will show up on the 'Board' category for Board and Staff.",
            "required": 0,
            "conditional_logic": 0,
            "wrapper": {
                "width": "",
                "class": "",
                "id": ""
            },
            "collapsed": "",
            "min": 0,
            "max": 0,
            "layout": "table",
            "button_label": "Add Row",
            "sub_fields": [
                {
                    "key": "field_630f847b0c331",
                    "label": "Item",
                    "name": "item",
                    "aria-label": "",
                    "type": "wysiwyg",
                    "instructions": "",
                    "required": 0,
                    "conditional_logic": 0,
                    "wrapper": {
                        "width": "",
                        "class": "",
                        "id": ""
                    },
                    "default_value": "",
                    "tabs": "all",
                    "toolbar": "full",
                    "media_upload": 1,
                    "delay": 0,
                    "parent_repeater": "field_630f84670c330"
                }
            ],
            "rows_per_page": 20
        },
        {
            "key": "field_66a3e06aba63d",
            "label": "SEO",
            "name": "",
            "aria-label": "",
            "type": "tab",
            "instructions": "",
            "required": 0,
            "conditional_logic": 0,
            "wrapper": {
                "width": "",
                "class": "",
                "id": ""
            },
            "placement": "top",
            "endpoint": 0,
            "selected": 0
        },
        {
            "key": "field_64e77d61ed182",
            "label": "Seo",
            "name": "seo",
            "aria-label": "",
            "type": "group",
            "instructions": "",
            "required": 0,
            "conditional_logic": 0,
            "wrapper": {
                "width": "",
                "class": "",
                "id": ""
            },
            "layout": "block",
            "sub_fields": [
                {
                    "key": "field_64e77d6bed183",
                    "label": "Description",
                    "name": "description",
                    "aria-label": "",
                    "type": "textarea",
                    "instructions": "",
                    "required": 0,
                    "conditional_logic": 0,
                    "wrapper": {
                        "width": "",
                        "class": "",
                        "id": ""
                    },
                    "default_value": "",
                    "placeholder": "",
                    "maxlength": "",
                    "rows": "",
                    "new_lines": ""
                }
            ]
        }
    ],
    "location": [
        [
            {
                "param": "options_page",
                "operator": "==",
                "value": "acf-options-sitewide-data"
            }
        ]
    ],
    "menu_order": 0,
    "position": "normal",
    "style": "default",
    "label_placement": "top",
    "instruction_placement": "label",
    "hide_on_screen": "",
    "active": true,
    "description": "",
    "show_in_rest": 0,
    "modified": 1722015896
}
